heatmapx/__init__.py
heatmapx/_thermograph.py
heatmapx-0.3.0.dist-info/METADATA
heatmapx-0.3.0.dist-info/LICENSE
heatmapx-0.3.0.dist-info/WHEEL
heatmapx-0.3.0.dist-info/RECORD
