Metadata-Version: 2.1
Name: heatmapx
Version: 0.3.0
Summary: Flexible, intuitive heatmap creation on NetworkX graphs
License: BSD-3-Clause
Author: drmrd
Requires-Python: >=3.9,<4.0
Classifier: License :: OSI Approved :: BSD License
Classifier: Programming Language :: Python :: 3
Classifier: Programming Language :: Python :: 3.9
Classifier: Programming Language :: Python :: 3.10
Classifier: Programming Language :: Python :: 3.11
Requires-Dist: networkx (>=2.6.0,<3.0.0)
